django_agent_trust/__init__.py
django_agent_trust/admin.py
django_agent_trust/apps.py
django_agent_trust/conf.py
django_agent_trust/context_processors.py
django_agent_trust/decorators.py
django_agent_trust/middleware.py
django_agent_trust/models.py
django_agent_trust/signals.py
django_agent_trust/migrations/0001_initial.py
django_agent_trust/migrations/__init__.py
django_agent_trust-1.1.0.dist-info/METADATA
django_agent_trust-1.1.0.dist-info/WHEEL
django_agent_trust-1.1.0.dist-info/licenses/LICENSE
django_agent_trust-1.1.0.dist-info/RECORD
