Metadata-Version: 2.1
Name: django-agent-trust
Version: 1.1.0
Summary: A framework for managing agent trust, such as public vs. private computers.
Project-URL: Documentation, https://django-agent-trust-official.readthedocs.io/
Project-URL: Homepage, https://github.com/django-otp/django-agent-trust
Author-email: Peter Sagerson <psagers@ignorare.net>
License-Expression: Unlicense
License-File: LICENSE
Classifier: Development Status :: 5 - Production/Stable
Classifier: Framework :: Django
Classifier: Intended Audience :: Developers
Classifier: License :: OSI Approved :: The Unlicense (Unlicense)
Classifier: Programming Language :: Python :: 3
Classifier: Programming Language :: Python :: 3 :: Only
Classifier: Topic :: Security
Classifier: Topic :: Software Development :: Libraries :: Python Modules
Requires-Python: >=3.7
Requires-Dist: django>=2.2
